decoder.v
module decoder(
    input [15:0] instruction,
    
    output [2:0] opcode,
    output [2:0] rd,
    output [2:0] rs1,
    output [2:0] rs2,
    
    // Load and JMP fields
    output [7:0] immediate_addr,
    
    //instruction type flags
    output is_jmp,
    output is_load,
    output is_rtype
    );

    assign opcode = instruction[15:13];
    assign rd = instruction[12:10];
    assign rs1 = instruction[9:7];
    assign rs2 = instruction[6:4];
    assign immediate_addr = instruction[7:0];

    //instruction type detection
    assign is_jmp = (opcode == 3'b111);
    assign is_load = (opcode == 3'b110);
    assign is_rtype = !(is_jmp || is_load);
    //these flags are 'wire' type because they are used as control signals for executing the instructions.
    //So live values of these flags are needed in the next clock cycle.
endmodule

decoder_tb.v
module decoder_tb;

    reg [15:0] instruction;
    wire [2:0] opcode;
    wire [2:0] rd;
    wire [2:0] rs1;
    wire [2:0] rs2;
    wire [7:0] immediate_addr; 
    wire is_rtype;
    wire is_load;
    wire is_jmp;

    //INSTANTIATION
    decoder uut(
        .instruction(instruction),
        .opcode(opcode),
        .rd(rd),
        .rs1(rs1),
        .rs2(rs2),
        .immediate_addr(immediate_addr),
        .is_jmp(is_jmp),
        .is_load(is_load),
        .is_rtype(is_rtype)
    );

    initial begin
        $monitor("Time=%0t | instruction=%b | opcode=%b | rd=%b | rs1=%b | rs2=%b | immediate_addr=%b | is_jmp=%b | is_load=%b | is_rtype=%b",
                 $time, instruction, opcode, rd, rs1, rs2, immediate_addr, is_jmp, is_load, is_rtype);
    end

    initial begin
        $dumpfile("decoder_tb.vcd");
        $dumpvars(0, decoder_tb);

        // Test case 1: R-type instruction
        instruction = 16'b000_001_010_011_0000; // opcode=000, rd=001, rs1=010, rs2=011
        #10;

        //Test case 2: AND instruction
        instruction = 16'b010_101_010_011_0000; // opcode=010, rd=101, rs1=010, rs2=011
        #10;

        // Test case 3: Load instruction
        instruction = 16'b110_011_00_00000101; #10;

        // Test case 4: Jump instruction
        instruction = 16'b111_00000_00000100; #10;

        //test case 5: NOP instruction
        instruction = 16'b000_000_000_000_0000; #10;

        //Rapidly change instruction and verify
        instruction = 16'b000_001_010_011_0000; #2;
        instruction = 16'b111_00000_00000100;   #2;
        instruction = 16'b110_011_00_00000101;  #2;
        instruction = 16'b000_001_010_011_0000; #2;

        $finish;
    end

endmodule

decoder_tb.vcd
$date
	Wed Jun 24 23:00:44 2026
$end
$version
	Icarus Verilog
$end
$timescale
	1s
$end
$scope module decoder_tb $end
$var wire 8 ! immediate_addr [7:0] $end
$var wire 1 " is_jmp $end
$var wire 1 # is_load $end
$var wire 1 $ is_rtype $end
$var wire 3 % opcode [2:0] $end
$var wire 3 & rd [2:0] $end
$var wire 3 ' rs1 [2:0] $end
$var wire 3 ( rs2 [2:0] $end
$var reg 16 ) instruction [15:0] $end
$scope module uut $end
$var wire 8 * immediate_addr [7:0] $end
$var wire 16 + instruction [15:0] $end
$var wire 1 " is_jmp $end
$var wire 1 # is_load $end
$var wire 1 $ is_rtype $end
$var wire 3 , opcode [2:0] $end
$var wire 3 - rd [2:0] $end
$var wire 3 . rs1 [2:0] $end
$var wire 3 / rs2 [2:0] $end
$upscope $end
$upscope $end
$enddefinitions $end
#0
$dumpvars
b11 /
b10 .
b1 -
b0 ,
b10100110000 +
b110000 *
b10100110000 )
b11 (
b10 '
b1 &
b0 %
1$
0#
0"
b110000 !
$end
#10
b10 %
b10 ,
b101 &
b101 -
b101010100110000 )
b101010100110000 +
#20
0$
1#
b110 %
b110 ,
b11 &
b11 -
b0 '
b0 .
b0 (
b0 /
b101 !
b101 *
b1100110000000101 )
b1100110000000101 +
#30
1"
0#
b111 %
b111 ,
b0 &
b0 -
b100 !
b100 *
b1110000000000100 )
b1110000000000100 +
#40
1$
0"
b0 %
b0 ,
b0 !
b0 *
b0 )
b0 +
#50
b1 &
b1 -
b10 '
b10 .
b11 (
b11 /
b110000 !
b110000 *
b10100110000 )
b10100110000 +
#52
0$
1"
b111 %
b111 ,
b0 &
b0 -
b0 '
b0 .
b0 (
b0 /
b100 !
b100 *
b1110000000000100 )
b1110000000000100 +
#54
0"
1#
b110 %
b110 ,
b11 &
b11 -
b101 !
b101 *
b1100110000000101 )
b1100110000000101 +
#56
1$
0#
b0 %
b0 ,
b1 &
b1 -
b10 '
b10 .
b11 (
b11 /
b110000 !
b110000 *
b10100110000 )
b10100110000 +
