program_counter.v
module program_counter(
    input clk,
    input rst,
    input jump_enable,
    input [7:0] jump_addr,
    output reg [7:0] pc
);

    always @(posedge clk, posedge rst) begin
        if(rst) 
            pc <= 8'b0;
        else if(jump_enable)
            pc <= jump_addr;
        else
            pc <= pc + 1;

    end
endmodule

program_counter_tb.v
module program_counter_tb;

    // Part 2 — signals
    reg clk;
    reg rst;
    reg jump_enable;
    reg [7:0] jump_addr;
    wire [7:0] pc;

    // Part 3 — instantiate
    program_counter uut(
        .clk(clk),
        .rst(rst),
        .jump_enable(jump_enable),
        .jump_addr(jump_addr),
        .pc(pc)
    );

    // Part 4 — clock
    initial clk = 0;
    always #5 clk = ~clk;

    // Monitor — prints every time any signal changes
    initial begin
        $monitor("Time=%0t | rst=%b | jump_en=%b | jump_addr=%0d | pc=%0d",
                  $time, rst, jump_enable, jump_addr, pc);
    end

    // Part 5 — stimulus
    initial begin
        $dumpfile("pc_tb.vcd");
        $dumpvars(0, program_counter_tb);

        // Test 1 — Reset
        rst = 1; jump_enable = 0; jump_addr = 0;
        #10;
        // Expected: pc = 0

        // Test 2 — Normal increment
        rst = 0;
        #10; // Expected: pc = 1
        #10; // Expected: pc = 2
        #10; // Expected: pc = 3
        #10; // Expected: pc = 4

        // Test 3 — Jump
        jump_enable = 1; jump_addr = 8'd20;
        #10;
        // Expected: pc = 20
        jump_enable = 0;

        // Test 4 — Resume incrementing after jump
        #10; // Expected: pc = 21
        #10; // Expected: pc = 22
        #10; // Expected: pc = 23

        // Test 5 — Reset in the middle
        rst = 1;
        #10;
        // Expected: pc = 0
        rst = 0;
        #10; // Expected: pc = 1

        $finish;
    end

endmodule

program_counter_tb.vcd
$date
	Mon Jun 22 20:35:59 2026
$end
$version
	Icarus Verilog
$end
$timescale
	1s
$end
$scope module program_counter_tb $end
$var wire 8 ! pc [7:0] $end
$var reg 1 " clk $end
$var reg 8 # jump_addr [7:0] $end
$var reg 1 $ jump_enable $end
$var reg 1 % rst $end
$scope module uut $end
$var wire 1 & clk $end
$var wire 8 ' jump_addr [7:0] $end
$var wire 1 ( jump_enable $end
$var wire 1 ) rst $end
$var reg 8 * pc [7:0] $end
$upscope $end
$upscope $end
$enddefinitions $end
#0
$dumpvars
b0 *
1)
0(
b0 '
0&
1%
0$
b0 #
0"
b0 !
$end
#5
1"
1&
#10
0"
0&
0%
0)
#15
b1 *
b1 !
1"
1&
#20
0"
0&
#25
b10 *
b10 !
1"
1&
#30
0"
0&
#35
b11 *
b11 !
1"
1&
#40
0"
0&
#45
b100 *
b100 !
1"
1&
#50
0"
0&
b10100 #
b10100 '
1$
1(
#55
b10100 *
b10100 !
1"
1&
#60
0"
0&
0$
0(
#65
b10101 *
b10101 !
1"
1&
#70
0"
0&
#75
b10110 *
b10110 !
1"
1&
#80
0"
0&
#85
b10111 *
b10111 !
1"
1&
#90
b0 *
b0 !
0"
0&
1%
1)
#95
1"
1&
#100
0"
0&
0%
0)
#105
b1 *
b1 !
1"
1&
