data_memory.v
module data_memory(
    input clk,
    input rst,
    input mem_read, // read enable
    input mem_write, // write enable
    input [7:0] addr, // Address 8-bits for 256 locations
    input [7:0] write_data, // Data to write
    output reg [7:0] read_data // Data to read
);

    //256 locations of 8 bits each (256 x 8 bits)[256B data memory]
    //Stores data values not INSTRUCTIONS
    reg [7:0] memory [0:255];
    integer i;

    //write: sequential clock driven
    always @(posedge clk or posedge rst) begin
        if(rst) begin
            for(i=0; i<256; i=i+1) begin
                memory[i] <= 8'b0;
            end
        end else if(mem_write) begin
            memory[addr] <= write_data;
        end
    end

    //read: combinational
    always @(*) begin
        if(mem_read) begin
            read_data = memory[addr];
        end
        else
            read_data = 8'b0;
    end
endmodule

alu.v
module alu(
    input [7:0] a,
    input [7:0] b,
    input [2:0] opcode,
    output reg [7:0] result,
    output reg carry,
    output reg zero_flag
);
    always @(*)
       begin
        carry = 0;
        case(opcode)
            3'b000: {carry, result} = a + b; //ADD
            3'b001: {carry, result} = {1'b0, a} - {1'b0, b}; //SUB
            3'b010: result = a & b; //AND
            3'b011: result = a | b; //OR
            3'b100: result = ~ a; //NOT
            3'b101: result = a; //MOV
            default : result = 8'b0;
        endcase
        zero_flag = (result == 8'b0);
       end
endmodule

register_file.v
module register_file(
    input clk,
    input rst,
    input write_enable,
    input [2:0] read_addr1, // Address of first source register
    input [2:0] read_addr2, // Address of second source register
    input [2:0] write_addr, // Address of destination register
    input [7:0] write_data, // Data to be written to the destination register
    output reg[7:0] read_data1, // Data from first source register
    output reg[7:0] read_data2 // Data from second source register
);
    integer i;

    reg [7:0] registers [0:7];
    always @(*) begin

        read_data1 = (write_enable && (read_addr1 == write_addr)) ? write_data : registers[read_addr1]; // rectifying the read-before-write hazard
        read_data2 = (write_enable && (read_addr2 == write_addr)) ? write_data : registers[read_addr2];
    end

    always @(posedge clk or posedge rst) begin
        
        if(rst) begin
            for(i=0; i<8; i=i+1)begin
                registers[i] <= 8'b0;
            end

        end else if(write_enable) begin
            registers[write_addr] <= write_data;
        end
    end
endmodule

control_unit.v
module control_unit(
    input [2:0] opcode,
    output reg [2:0] alu_op,
    output reg mem_read,
    output reg mem_write,
    output reg reg_write,
    output reg jump_enable,
    output reg wb_select //writeback select: =0 while writing back from ALU ; =1 while writing back from memory
);



    always @(*) begin
        // Initializing all signals with 0 value
        alu_op = 3'b000;
        mem_read = 1'b0;
        mem_write = 1'b0;
        reg_write = 1'b0;
        jump_enable = 1'b0;
        wb_select = 1'b0;

        case (opcode)
            3'b000: begin alu_op=3'b000; reg_write=1; end // ADD
            3'b001: begin alu_op=3'b001; reg_write=1; end // SUB
            3'b010: begin alu_op=3'b010; reg_write=1; end // AND
            3'b011: begin alu_op=3'b011; reg_write=1; end // OR
            3'b100: begin alu_op=3'b100; reg_write=1; end // NOT
            3'b101: begin alu_op=3'b101; reg_write=1; end // MOV
            3'b110: begin mem_read=1'b1; reg_write=1; wb_select=1'b1; end // LOAD
            3'b111: begin jump_enable=1'b1; end // JUMP
        endcase
    end
endmodule

decoder.v
module decoder(
    input [15:0] instruction,
    
    output [2:0] opcode,
    output [2:0] rd,
    output [2:0] rs1,
    output [2:0] rs2,
    
    // Load and JMP fields
    output [7:0] immediate_addr,
    
    //instruction type flags
    output is_jmp,
    output is_load,
    output is_rtype
    );

    assign opcode = instruction[15:13];
    assign rd = instruction[12:10];
    assign rs1 = instruction[9:7];
    assign rs2 = instruction[6:4];
    assign immediate_addr = instruction[7:0];

    //instruction type detection
    assign is_jmp = (opcode == 3'b111);
    assign is_load = (opcode == 3'b110);
    assign is_rtype = !(is_jmp || is_load);
    //these flags are 'wire' type because they are used as control signals for executing the instructions.
    //So live values of these flags are needed in the next clock cycle.
endmodule

instruction_memory.v
//PC → [Instruction Memory] → instruction bits → [Decoder]
//[15:13] — opcode    (3 bits — 8 possible instructions)
// [12:10] — dest reg  (3 bits — Rd)
// [9:7]   — src reg1  (3 bits — Rs1)
// [6:4]   — src reg2  (3 bits — Rs2)
// [3:0]   — unused / immediate (4 bits)

module instruction_memory(
    input [7:0] addr,
    output reg [15:0] instruction
);
    //Memory - 256 locations of 16 bits each (256 x 16 bits)
    reg [15:0] memory [255:0];
    integer i;
    //Preload the instruction memory with some instructions
    initial begin
        // Format: opcode(3) | Rd(3) | Rs1(3) | Rs2(3) | unused(4)
        // ADD R1, R2, R3 → opcode=000, Rd=001, Rs1=010, Rs2=011
        
        for(i=0; i<256; i=i+1) begin
            memory[i] = 16'b0000000000000000; // Initialize all memory to NOP(No operation) (or 0)
        end
        // For your CPU to execute anything, there has to be something already sitting at memory[0] before the simulation even starts ticking.
        // A real CPU has the same problem — that's literally what "bootstrapping" means. 
        // On real hardware this is solved by things like a BIOS/bootloader burned into ROM, or a .hex/.mem file loaded by a programmer before power-on. 
        memory[0] = 16'b000_001_010_011_0000;
        memory[1] = 16'b001_100_001_011_0000;
        memory[2] = 16'b010_101_010_011_0000;
        memory[3] = 16'b011_110_001_010_0000;
        memory[4] = 16'b100_111_001_000_0000;
        memory[5] = 16'b101_001_010_000_0000;
        memory[6] = 16'b111_000_00_00000100; //JMP to address 4 (Here '111' is the opcode for JMP, and '00000100' is the address to jump to)

    end

    always @(*) begin
        instruction = memory[addr];
    end
endmodule

program_counter.v
module program_counter(
    input clk,
    input rst,
    input jump_enable,
    input [7:0] jump_addr,
    output reg [7:0] pc
);

    always @(posedge clk, posedge rst) begin
        if(rst) 
            pc <= 8'b0;
        else if(jump_enable)
            pc <= jump_addr;
        else
            pc <= pc + 1;

    end
endmodule

top.v
module top(
    input clk,
    input rst
);
    // Internal wires - connections between all the modules

    // Program Counter
    wire [7:0] pc;
    wire [7:0] jump_addr;

    // Instruction Memory
    wire [15:0] instruction;

    //Decoder outputs
    wire [2:0] opcode;
    wire [2:0] rd;
    wire [2:0] rs1;
    wire [2:0] rs2;
    wire [7:0] imm_addr;
    wire is_rtype;
    wire is_load;
    wire is_jmp;

    //jump address is the same as immediate address of the decoder/ instruction so:
    assign jump_addr = imm_addr;
    
    //Control Unit Outputs
    wire [2:0] alu_op;
    wire reg_write;
    wire mem_read;
    wire mem_write;
    wire jump_enable;
    wire wb_select;

    // Register File outputs
    wire [7:0] read_data1;
    wire [7:0] read_data2;

    // Data Memory outputs
    wire [7:0] mem_read_data;

    //ALU Outputs
    wire [7:0] alu_result;
    wire carry;
    wire Zero_flag;

    // Writeback mux output
    wire [7:0] writeback_data;
    //Writeback MUX
    assign writeback_data = wb_select ? mem_read_data : alu_result;


    //MODULE INSTANTIATIONS
    // 1. Program Counter
    program_counter pc_inst(
        .clk(clk),
        .rst(rst),
        .jump_enable(jump_enable),
        .jump_addr(jump_addr),
        .pc(pc)
    );

    // 2. Instruction Memory
    instruction_memory imem_inst(
        .addr(pc),
        .instruction(instruction)
    );

    // 3. Decoder
    decoder dec_inst(
        .instruction(instruction),
        .opcode(opcode),
        .rd(rd),
        .rs1(rs1),
        .rs2(rs2),
        .immediate_addr(imm_addr),
        .is_jmp(is_jmp),
        .is_load(is_load),
        .is_rtype(is_rtype)
    );

    // 4. Control Unit
    control_unit cu_inst(
        .opcode(opcode),
        .alu_op(alu_op),
        .mem_read(mem_read),
        .reg_write(reg_write),
        .mem_write(mem_write),
        .jump_enable(jump_enable),
        .wb_select(wb_select)
    );

    // 5. Register File
    register_file rf_inst(
        .clk(clk),
        .rst(rst),
        .write_enable(reg_write),
        .read_addr1(rs1),
        .read_addr2(rs2),
        .write_addr(rd),
        .write_data(writeback_data),
        .read_data1(read_data1),
        .read_data2(read_data2)
    );

    //6. ALU
    alu alu_inst(
        .a(read_data1),
        .b(read_data2),
        .opcode(alu_op),
        .result(alu_result),
        .carry(carry),
        .zero_flag(zero_flag)
    );

    // 7. Data Memory
    data_memory dmem_inst(
        .clk(clk),
        .rst(rst),
        .mem_read(mem_read),
        .mem_write(mem_write),
        .addr(imm_addr),
        .write_data(read_data1),
        .read_data(mem_read_data)
    );

endmodule

top_tb.v
module top_tb;

    reg clk;
    reg rst;

    top uut(
        .clk(clk),
        .rst(rst)
    );

    initial clk = 0;
    always #5 clk = ~clk;

    // Monitor — watch PC and instruction every cycle
    initial begin
        $monitor("Time=%0t | PC=%0d | instr=%b | opcode=%b",$time,
                  uut.pc,
                  uut.instruction,
                  uut.opcode);
    end

    initial begin
        $dumpfile("top_tb.vcd");
        $dumpvars(0, top_tb);

        // Reset processor
        rst = 1; #20;
        rst = 0;
        
        #200;

        $finish;
    end

endmodule

top_tb.vcd
$date
	Sun Jun 28 12:24:46 2026
$end
$version
	Icarus Verilog
$end
$timescale
	1s
$end
$scope module top_tb $end
$var reg 1 ! clk $end
$var reg 1 " rst $end
$scope module uut $end
$var wire 3 # alu_op [2:0] $end
$var wire 8 $ alu_result [7:0] $end
$var wire 1 % carry $end
$var wire 1 & clk $end
$var wire 8 ' imm_addr [7:0] $end
$var wire 16 ( instruction [15:0] $end
$var wire 1 ) is_jmp $end
$var wire 1 * is_load $end
$var wire 1 + is_rtype $end
$var wire 8 , jump_addr [7:0] $end
$var wire 1 - jump_enable $end
$var wire 1 . mem_read $end
$var wire 8 / mem_read_data [7:0] $end
$var wire 1 0 mem_write $end
$var wire 3 1 opcode [2:0] $end
$var wire 8 2 pc [7:0] $end
$var wire 3 3 rd [2:0] $end
$var wire 8 4 read_data1 [7:0] $end
$var wire 8 5 read_data2 [7:0] $end
$var wire 1 6 reg_write $end
$var wire 3 7 rs1 [2:0] $end
$var wire 3 8 rs2 [2:0] $end
$var wire 1 9 rst $end
$var wire 1 : wb_select $end
$var wire 8 ; writeback_data [7:0] $end
$var wire 1 < zero_flag $end
$scope module pc_inst $end
$var wire 1 & clk $end
$var wire 8 = jump_addr [7:0] $end
$var wire 1 - jump_enable $end
$var wire 1 9 rst $end
$var reg 8 > pc [7:0] $end
$upscope $end
$scope module imem_inst $end
$var wire 8 ? addr [7:0] $end
$var integer 32 @ i [31:0] $end
$var reg 16 A instruction [15:0] $end
$upscope $end
$scope module dec_inst $end
$var wire 8 B immediate_addr [7:0] $end
$var wire 16 C instruction [15:0] $end
$var wire 1 ) is_jmp $end
$var wire 1 * is_load $end
$var wire 1 + is_rtype $end
$var wire 3 D opcode [2:0] $end
$var wire 3 E rd [2:0] $end
$var wire 3 F rs1 [2:0] $end
$var wire 3 G rs2 [2:0] $end
$upscope $end
$scope module cu_inst $end
$var wire 3 H opcode [2:0] $end
$var reg 3 I alu_op [2:0] $end
$var reg 1 J jump_enable $end
$var reg 1 K mem_read $end
$var reg 1 L mem_write $end
$var reg 1 M reg_write $end
$var reg 1 N wb_select $end
$upscope $end
$scope module rf_inst $end
$var wire 1 & clk $end
$var wire 3 O read_addr1 [2:0] $end
$var wire 3 P read_addr2 [2:0] $end
$var wire 1 9 rst $end
$var wire 3 Q write_addr [2:0] $end
$var wire 8 R write_data [7:0] $end
$var wire 1 6 write_enable $end
$var integer 32 S i [31:0] $end
$var reg 8 T read_data1 [7:0] $end
$var reg 8 U read_data2 [7:0] $end
$upscope $end
$scope module alu_inst $end
$var wire 8 V a [7:0] $end
$var wire 8 W b [7:0] $end
$var wire 3 X opcode [2:0] $end
$var reg 1 Y carry $end
$var reg 8 Z result [7:0] $end
$var reg 1 [ zero_flag $end
$upscope $end
$scope module dmem_inst $end
$var wire 8 \ addr [7:0] $end
$var wire 1 & clk $end
$var wire 1 . mem_read $end
$var wire 1 0 mem_write $end
$var wire 1 9 rst $end
$var wire 8 ] write_data [7:0] $end
$var integer 32 ^ i [31:0] $end
$var reg 8 _ read_data [7:0] $end
$upscope $end
$upscope $end
$upscope $end
$enddefinitions $end
#0
$dumpvars
b0 _
b100000000 ^
b0 ]
b10000000 \
1[
b0 Z
0Y
b101 X
b0 W
b0 V
b0 U
b0 T
b1000 S
b0 R
b10 Q
b0 P
b1 O
0N
1M
1L
0K
0J
b101 I
b101 H
b0 G
b1 F
b10 E
b101 D
b1010100010000000 C
b10000000 B
b1010100010000000 A
b100000000 @
b0 ?
b0 >
b10000000 =
1<
b0 ;
0:
19
b0 8
b1 7
16
b0 5
b0 4
b10 3
b0 2
b101 1
10
b0 /
0.
0-
b10000000 ,
1+
0*
0)
b1010100010000000 (
b10000000 '
0&
0%
b0 $
b101 #
1"
0!
$end
#5
b100000000 ^
b1000 S
1!
1&
#10
0!
0&
#15
b1000 S
b100000000 ^
1!
1&
#20
0!
0&
0"
09
#25
1M
16
b0 I
b0 #
b0 X
b0 1
b0 D
b0 H
b11 3
b11 E
b11 Q
b10 8
b10 G
b10 P
b10100000 '
b10100000 B
b10100000 \
b10100000 ,
b10100000 =
b110010100000 A
b110010100000 (
b110010100000 C
b1 >
b1 2
b1 ?
1!
1&
#30
0!
0&
#35
b1 I
b1 #
b1 X
1M
16
b1 1
b1 D
b1 H
b100 3
b100 E
b100 Q
b11 7
b11 F
b11 O
b1 8
b1 G
b1 P
b10010000 '
b10010000 B
b10010000 \
b10010000 ,
b10010000 =
b11000110010000 A
b11000110010000 (
b11000110010000 C
b10 >
b10 2
b10 ?
1!
1&
#40
0!
0&
#45
1M
16
b10 I
b10 #
b10 X
b10 1
b10 D
b10 H
b101 3
b101 E
b101 Q
b10 8
b10 G
b10 P
b10100000 '
b10100000 B
b10100000 \
b10100000 ,
b10100000 =
b101010110100000 A
b101010110100000 (
b101010110100000 C
b11 >
b11 2
b11 ?
1!
1&
#50
0!
0&
#55
1M
16
b11 I
b11 #
b11 X
b11 1
b11 D
b11 H
b110 3
b110 E
b110 Q
b111100110100000 A
b111100110100000 (
b111100110100000 C
b100 >
b100 2
b100 ?
1!
1&
#60
0!
0&
#65
b11111111 ;
b11111111 R
0[
0<
b11111111 Z
b11111111 $
1M
16
b100 I
b100 #
b100 X
b100 1
b100 D
b100 H
b111 3
b111 E
b111 Q
b0 8
b0 G
b0 P
b10000000 '
b10000000 B
b10000000 \
b10000000 ,
b10000000 =
b1001110110000000 A
b1001110110000000 (
b1001110110000000 C
b101 >
b101 2
b101 ?
1!
1&
#70
0!
0&
#75
1[
1<
b0 ;
b0 R
0Y
0%
b0 Z
b0 $
0+
1J
1-
0M
06
b0 I
b0 #
b0 X
b0 U
b0 5
b0 W
b0 T
b0 4
b0 V
b0 ]
1)
b111 1
b111 D
b111 H
b0 3
b0 E
b0 Q
b0 7
b0 F
b0 O
b0 '
b0 B
b0 \
b0 ,
b0 =
b1110000000000000 A
b1110000000000000 (
b1110000000000000 C
b110 >
b110 2
b110 ?
1!
1&
#80
0!
0&
#85
1+
1M
16
b101 I
b101 #
b101 X
0J
0-
0)
b101 1
b101 D
b101 H
b10 3
b10 E
b10 Q
b1 7
b1 F
b1 O
b10000000 '
b10000000 B
b10000000 \
b10000000 ,
b10000000 =
b1010100010000000 A
b1010100010000000 (
b1010100010000000 C
b0 >
b0 2
b0 ?
1!
1&
#90
0!
0&
#95
1M
16
b0 I
b0 #
b0 X
b0 1
b0 D
b0 H
b11 3
b11 E
b11 Q
b10 8
b10 G
b10 P
b10100000 '
b10100000 B
b10100000 \
b10100000 ,
b10100000 =
b110010100000 A
b110010100000 (
b110010100000 C
b1 >
b1 2
b1 ?
1!
1&
#100
0!
0&
#105
b1 I
b1 #
b1 X
1M
16
b1 1
b1 D
b1 H
b100 3
b100 E
b100 Q
b11 7
b11 F
b11 O
b1 8
b1 G
b1 P
b10010000 '
b10010000 B
b10010000 \
b10010000 ,
b10010000 =
b11000110010000 A
b11000110010000 (
b11000110010000 C
b10 >
b10 2
b10 ?
1!
1&
#110
0!
0&
#115
1M
16
b10 I
b10 #
b10 X
b10 1
b10 D
b10 H
b101 3
b101 E
b101 Q
b10 8
b10 G
b10 P
b10100000 '
b10100000 B
b10100000 \
b10100000 ,
b10100000 =
b101010110100000 A
b101010110100000 (
b101010110100000 C
b11 >
b11 2
b11 ?
1!
1&
#120
0!
0&
#125
1M
16
b11 I
b11 #
b11 X
b11 1
b11 D
b11 H
b110 3
b110 E
b110 Q
b111100110100000 A
b111100110100000 (
b111100110100000 C
b100 >
b100 2
b100 ?
1!
1&
#130
0!
0&
#135
b11111111 ;
b11111111 R
0[
0<
b11111111 Z
b11111111 $
1M
16
b100 I
b100 #
b100 X
b100 1
b100 D
b100 H
b111 3
b111 E
b111 Q
b0 8
b0 G
b0 P
b10000000 '
b10000000 B
b10000000 \
b10000000 ,
b10000000 =
b1001110110000000 A
b1001110110000000 (
b1001110110000000 C
b101 >
b101 2
b101 ?
1!
1&
#140
0!
0&
#145
1[
1<
b0 ;
b0 R
0Y
0%
b0 Z
b0 $
0+
1J
1-
0M
06
b0 I
b0 #
b0 X
b0 U
b0 5
b0 W
b0 T
b0 4
b0 V
b0 ]
1)
b111 1
b111 D
b111 H
b0 3
b0 E
b0 Q
b0 7
b0 F
b0 O
b0 '
b0 B
b0 \
b0 ,
b0 =
b1110000000000000 A
b1110000000000000 (
b1110000000000000 C
b110 >
b110 2
b110 ?
1!
1&
#150
0!
0&
#155
1+
1M
16
b101 I
b101 #
b101 X
0J
0-
0)
b101 1
b101 D
b101 H
b10 3
b10 E
b10 Q
b1 7
b1 F
b1 O
b10000000 '
b10000000 B
b10000000 \
b10000000 ,
b10000000 =
b1010100010000000 A
b1010100010000000 (
b1010100010000000 C
b0 >
b0 2
b0 ?
1!
1&
#160
0!
0&
#165
1M
16
b0 I
b0 #
b0 X
b0 1
b0 D
b0 H
b11 3
b11 E
b11 Q
b10 8
b10 G
b10 P
b10100000 '
b10100000 B
b10100000 \
b10100000 ,
b10100000 =
b110010100000 A
b110010100000 (
b110010100000 C
b1 >
b1 2
b1 ?
1!
1&
#170
0!
0&
#175
b1 I
b1 #
b1 X
1M
16
b1 1
b1 D
b1 H
b100 3
b100 E
b100 Q
b11 7
b11 F
b11 O
b1 8
b1 G
b1 P
b10010000 '
b10010000 B
b10010000 \
b10010000 ,
b10010000 =
b11000110010000 A
b11000110010000 (
b11000110010000 C
b10 >
b10 2
b10 ?
1!
1&
#180
0!
0&
#185
1M
16
b10 I
b10 #
b10 X
b10 1
b10 D
b10 H
b101 3
b101 E
b101 Q
b10 8
b10 G
b10 P
b10100000 '
b10100000 B
b10100000 \
b10100000 ,
b10100000 =
b101010110100000 A
b101010110100000 (
b101010110100000 C
b11 >
b11 2
b11 ?
1!
1&
#190
0!
0&
#195
1M
16
b11 I
b11 #
b11 X
b11 1
b11 D
b11 H
b110 3
b110 E
b110 Q
b111100110100000 A
b111100110100000 (
b111100110100000 C
b100 >
b100 2
b100 ?
1!
1&
#200
0!
0&
#205
b11111111 ;
b11111111 R
0[
0<
b11111111 Z
b11111111 $
1M
16
b100 I
b100 #
b100 X
b100 1
b100 D
b100 H
b111 3
b111 E
b111 Q
b0 8
b0 G
b0 P
b10000000 '
b10000000 B
b10000000 \
b10000000 ,
b10000000 =
b1001110110000000 A
b1001110110000000 (
b1001110110000000 C
b101 >
b101 2
b101 ?
1!
1&
#210
0!
0&
#215
1[
1<
b0 ;
b0 R
0Y
0%
b0 Z
b0 $
0+
1J
1-
0M
06
b0 I
b0 #
b0 X
b0 U
b0 5
b0 W
b0 T
b0 4
b0 V
b0 ]
1)
b111 1
b111 D
b111 H
b0 3
b0 E
b0 Q
b0 7
b0 F
b0 O
b0 '
b0 B
b0 \
b0 ,
b0 =
b1110000000000000 A
b1110000000000000 (
b1110000000000000 C
b110 >
b110 2
b110 ?
1!
1&
