alu.v
module alu(
    input [7:0] a,
    input [7:0] b,
    input [2:0] opcode,
    output reg [7:0] result,
    output reg carry,
    output reg zero_flag
);
    always @(*)
       begin
        carry = 0;
        case(opcode)
            3'b000: {carry, result} = a + b; //ADD
            3'b001: {carry, result} = {1'b0, a} - {1'b0, b}; //SUB
            3'b010: result = a & b; //AND
            3'b011: result = a | b; //OR
            3'b100: result = ~ a; //NOT
            3'b101: result = a; //MOV
            default : result = 8'b0;
        endcase
        zero_flag = (result == 8'b0);
       end
endmodule

alu_tb.v
module alu_tb;
    reg [7:0] a, b;
    reg [2:0] opcode;
    wire [7:0] result;
    wire carry, zero_flag;

    // Instantiate ALU
    alu uut(
        .a(a), .b(b),
        .opcode(opcode),
        .result(result),
        .carry(carry),
        .zero_flag(zero_flag)
    );

    initial begin
        $dumpfile("alu_tb.vcd");
        $dumpvars(0, alu_tb);

        // Test ADD — normal
        a = 8'd10; b = 8'd5; opcode = 3'b000; #10;
        // Test ADD — with carry
        a = 8'd200; b = 8'd100; opcode = 3'b000; #10;
        // Test SUB — normal
        a = 8'd10; b = 8'd5; opcode = 3'b001; #10;
        // Test SUB — with borrow
        a = 8'd5; b = 8'd10; opcode = 3'b001; #10;
        // Test AND
        a = 8'b11001100; b = 8'b10101010; opcode = 3'b010; #10;
        // Test OR
        a = 8'b11001100; b = 8'b10101010; opcode = 3'b011; #10;
        // Test NOT
        a = 8'b10101010; b = 8'b0; opcode = 3'b100; #10;
        // Test MOV
        a = 8'd42; b = 8'b0; opcode = 3'b101; #10;
        // Test zero flag
        a = 8'd0; b = 8'd0; opcode = 3'b000; #10;

        $finish;
    end

    // Monitor outputs
    initial begin
        $monitor("Time=%0t a=%d b=%d opcode=%b result=%d carry=%b zero=%b",
                  $time, a, b, opcode, result, carry, zero_flag);
    end

endmodule

vcd/alu_tb.vcd
$date
	Fri Jun 19 20:41:11 2026
$end
$version
	Icarus Verilog
$end
$timescale
	1s
$end
$scope module alu_tb $end
$var wire 1 ! carry $end
$var wire 8 " result [7:0] $end
$var wire 1 # zero_flag $end
$var reg 8 $ a [7:0] $end
$var reg 8 % b [7:0] $end
$var reg 3 & opcode [2:0] $end
$scope module uut $end
$var wire 8 ' a [7:0] $end
$var wire 8 ( b [7:0] $end
$var wire 3 ) opcode [2:0] $end
$var reg 1 * carry $end
$var reg 8 + result [7:0] $end
$var reg 1 , zero_flag $end
$upscope $end
$upscope $end
$enddefinitions $end
#0
$dumpvars
0,
b1111 +
0*
b0 )
b101 (
b1010 '
b0 &
b101 %
b1010 $
0#
b1111 "
0!
$end
#10
1*
1!
b101100 +
b101100 "
b1100100 %
b1100100 (
b11001000 $
b11001000 '
#20
b101 +
b101 "
0*
0!
b1 &
b1 )
b101 %
b101 (
b1010 $
b1010 '
#30
1*
1!
b11111011 +
b11111011 "
b1010 %
b1010 (
b101 $
b101 '
#40
b10001000 +
b10001000 "
0*
0!
b10 &
b10 )
b10101010 %
b10101010 (
b11001100 $
b11001100 '
#50
b11101110 +
b11101110 "
b11 &
b11 )
#60
b1010101 +
b1010101 "
b100 &
b100 )
b0 %
b0 (
b10101010 $
b10101010 '
#70
b101010 +
b101010 "
b101 &
b101 )
b101010 $
b101010 '
#80
1,
1#
b0 +
b0 "
b0 &
b0 )
b0 $
b0 '
