control_unit.v
module control_unit(
    input [2:0] opcode,
    output reg [2:0] alu_op,
    output reg mem_read,
    output reg mem_write,
    output reg reg_write,
    output reg jump_enable,
    output reg wb_select //writeback select: =0 while writing back from ALU ; =1 while writing back from memory
);



    always @(*) begin
        // Initializing all signals with 0 value
        alu_op = 3'b000;
        mem_read = 1'b0;
        mem_write = 1'b0;
        reg_write = 1'b0;
        jump_enable = 1'b0;
        wb_select = 1'b0;

        case (opcode)
            3'b000: begin alu_op=3'b000; reg_write=1; end // ADD
            3'b001: begin alu_op=3'b001; reg_write=1; end // SUB
            3'b010: begin alu_op=3'b010; reg_write=1; end // AND
            3'b011: begin alu_op=3'b011; reg_write=1; end // OR
            3'b100: begin alu_op=3'b100; reg_write=1; end // NOT
            3'b101: begin alu_op=3'b101; reg_write=1; end // MOV
            3'b110: begin mem_read=1'b1; reg_write=1; wb_select=1'b1; end // LOAD
            3'b111: begin jump_enable=1'b1; end // JUMP
        endcase
    end
endmodule

control_unit_tb.v
module control_unit_tb;
    
    reg [2:0] opcode;
    wire [2:0] alu_op;
    wire mem_read;
    wire mem_write;
    wire reg_write;
    wire jump_enable;
    wire wb_select;

    // Instantiate the control unit
    control_unit uut(
        .opcode(opcode),
        .alu_op(alu_op),
        .mem_read(mem_read),
        .mem_write(mem_write),
        .reg_write(reg_write),
        .jump_enable(jump_enable),
        .wb_select(wb_select)
    );
    
    initial begin
        $monitor("Time=%0t | opcode=%b | alu_op=%b | mem_read=%b | mem_write=%b | reg_write=%b | jump_enable=%b | wb_select=%b",
                 $time, opcode, alu_op, mem_read, mem_write, reg_write, jump_enable, wb_select);
    end

    initial begin
        $dumpfile("control_unit_tb.vcd");
        $dumpvars(0, control_unit_tb);

        // Applying test vectors
        opcode = 3'b000; #10;
        opcode = 3'b001; #10;
        opcode = 3'b010; #10;
        opcode = 3'b011; #10;
        opcode = 3'b100; #10;
        opcode = 3'b101; #10;
        opcode = 3'b110; #10;
        opcode = 3'b111; #10;
        opcode = 3'bxxx; #10; // Invalid opcode test
        $finish;
    end
endmodule

vcd/control_unit_tb.vcd
$date
	Fri Jun 26 21:50:51 2026
$end
$version
	Icarus Verilog
$end
$timescale
	1s
$end
$scope module control_unit_tb $end
$var wire 3 ! alu_op [2:0] $end
$var wire 1 " jump_enable $end
$var wire 1 # mem_read $end
$var wire 1 $ mem_write $end
$var wire 1 % reg_write $end
$var wire 1 & wb_select $end
$var reg 3 ' opcode [2:0] $end
$scope module uut $end
$var wire 3 ( opcode [2:0] $end
$var reg 3 ) alu_op [2:0] $end
$var reg 1 * jump_enable $end
$var reg 1 + mem_read $end
$var reg 1 , mem_write $end
$var reg 1 - reg_write $end
$var reg 1 . wb_select $end
$upscope $end
$upscope $end
$enddefinitions $end
#0
$dumpvars
0.
1-
0,
0+
0*
b0 )
b0 (
b0 '
0&
1%
0$
0#
0"
b0 !
$end
#10
b1 )
b1 !
1-
1%
b1 '
b1 (
#20
1-
1%
b10 )
b10 !
b10 '
b10 (
#30
1-
1%
b11 )
b11 !
b11 '
b11 (
#40
1-
1%
b100 )
b100 !
b100 '
b100 (
#50
1-
1%
b101 )
b101 !
b101 '
b101 (
#60
1+
1#
1-
1%
b0 )
b0 !
b110 '
b110 (
#70
1*
1"
0-
0%
0+
0#
b111 '
b111 (
#80
0*
0"
bx '
bx (
