instruction_memory.v
//PC → [Instruction Memory] → instruction bits → [Decoder]
//[15:13] — opcode    (3 bits — 8 possible instructions)
// [12:10] — dest reg  (3 bits — Rd)
// [9:7]   — src reg1  (3 bits — Rs1)
// [6:4]   — src reg2  (3 bits — Rs2)
// [3:0]   — unused / immediate (4 bits)

module instruction_memory(
    input [7:0] addr,
    output reg [15:0] instruction
);
    //Memory - 256 locations of 16 bits each (256 x 16 bits)
    reg [15:0] memory [255:0];
    integer i;
    //Preload the instruction memory with some instructions
    initial begin
        // Format: opcode(3) | Rd(3) | Rs1(3) | Rs2(3) | unused(4)
        // ADD R1, R2, R3 → opcode=000, Rd=001, Rs1=010, Rs2=011
        
        for(i=0; i<256; i=i+1) begin
            memory[i] = 16'b0000000000000000; // Initialize all memory to NOP(No operation) (or 0)
        end
        // For your CPU to execute anything, there has to be something already sitting at memory[0] before the simulation even starts ticking.
        // A real CPU has the same problem — that's literally what "bootstrapping" means. 
        // On real hardware this is solved by things like a BIOS/bootloader burned into ROM, or a .hex/.mem file loaded by a programmer before power-on. 
        memory[0] = 16'b000_001_010_011_0000;
        memory[1] = 16'b001_100_001_011_0000;
        memory[2] = 16'b010_101_010_011_0000;
        memory[3] = 16'b011_110_001_010_0000;
        memory[4] = 16'b100_111_001_000_0000;
        memory[5] = 16'b101_001_010_000_0000;
        memory[6] = 16'b111_000_00_00000100; //JMP to address 4 (Here '111' is the opcode for JMP, and '00000100' is the address to jump to)

    end

    always @(*) begin
        instruction = memory[addr];
    end
endmodule

instruction_memory_tb.v
`timescale 1ns/1ps

module instruction_memory_tb;

    reg  [7:0]  addr;
    wire [15:0] instruction;

    // Bit-field views of the fetched instruction, purely for readability
    // in the waveform viewer / $monitor output. These are NOT part of the
    // DUT — just testbench-side decoding so we can sanity-check fields
    // without doing bit-slicing math in our heads every time.
    wire [2:0] opcode = instruction[15:13];
    wire [2:0] rd     = instruction[12:10];
    wire [2:0] rs1    = instruction[9:7];
    wire [2:0] rs2    = instruction[6:4];
    wire [3:0] unused = instruction[3:0];

    integer errors = 0; // running tally — nonzero at the end means something's wrong
    integer i;           // loop variable for the address sweep test, module scope

    // Instantiate the DUT (Design Under Test)
    instruction_memory uut (
        .addr(addr),
        .instruction(instruction)
    );

    // Reusable check task: compares the DUT's instruction output against
    // an expected value, prints PASS/FAIL, and increments the error count
    // on mismatch. Doing this as a task instead of copy-pasting if-checks
    // 9 times means the comparison logic only has to be correct once.
    task check_instruction(input [7:0] test_addr, input [15:0] expected);
        begin
            addr = test_addr;
            #5; // let the combinational always@(*) block settle
            if (instruction !== expected) begin
                errors = errors + 1;
                $display("FAIL: addr=%0d  expected=%b  got=%b",
                          test_addr, expected, instruction);
            end else begin
                $display("PASS: addr=%0d  instruction=%b  (opcode=%b rd=%b rs1=%b rs2=%b unused=%b)",
                          test_addr, instruction, opcode, rd, rs1, rs2, unused);
            end
        end
    endtask

    initial begin
        $dumpfile("instruction_memory_tb.vcd");
        $dumpvars(0, instruction_memory_tb);

        $display("---- Test 1: ADD  (addr 0) ----");
        check_instruction(8'd0, 16'b000_001_010_011_0000);

        $display("---- Test 2: opcode=001 (addr 1) ----");
        check_instruction(8'd1, 16'b001_100_001_011_0000);

        $display("---- Test 3: opcode=010 (addr 2) ----");
        check_instruction(8'd2, 16'b010_101_010_011_0000);

        $display("---- Test 4: opcode=011 (addr 3) ----");
        check_instruction(8'd3, 16'b011_110_001_010_0000);

        $display("---- Test 5: opcode=100 (addr 4) ----");
        check_instruction(8'd4, 16'b100_111_001_000_0000);

        $display("---- Test 6: opcode=101 (addr 5) ----");
        check_instruction(8'd5, 16'b101_001_010_000_0000);

        $display("---- Test 7: JMP encoding (addr 6) ----");
        check_instruction(8'd6, 16'b111_000_00_00000100);

        $display("---- Test 8: NOP region, lower boundary (addr 7) ----");
        check_instruction(8'd7, 16'b0000000000000000);

        $display("---- Test 9: NOP region, mid-range spot check (addr 128) ----");
        check_instruction(8'd128, 16'b0000000000000000);

        $display("---- Test 10: NOP region, upper boundary (addr 255) ----");
        check_instruction(8'd255, 16'b0000000000000000);

        $display("---- Test 11: re-read addr 0 after walking through full range ----");
        // Confirms reads are stateless / purely combinational — revisiting
        // an earlier address gives the same result, i.e. reading doesn't
        // mutate memory and addr decode has no hidden order-dependence.
        check_instruction(8'd0, 16'b000_001_010_011_0000);

        $display("---- Test 12: rapid address sweep (combinational responsiveness) ----");
        // Walk every address from 0 to 9 with only #1 between changes
        // (instead of the usual #5) to make sure the always@(*) block
        // reacts on EVERY addr change, not just ones we pause long enough
        // to "let settle." If sensitivity were wrong (e.g. someone had
        // mistakenly written always@(posedge addr[0]) or similar), this
        // is the kind of test that would expose it.
        for (i = 0; i < 10; i = i + 1) begin
            addr = i;
            #1;
            $display("  sweep addr=%0d -> instruction=%b", i, instruction);
        end

        $display("--------------------------------------------------");
        if (errors == 0)
            $display("ALL TESTS PASSED");
        else
            $display("%0d TEST(S) FAILED", errors);
        $display("--------------------------------------------------");

        $finish;
    end

endmodule

vcd/instruction_memory_tb.vcd
$date
	Tue Jun 23 19:21:11 2026
$end
$version
	Icarus Verilog
$end
$timescale
	1ps
$end
$scope module instruction_memory_tb $end
$var wire 16 ! instruction [15:0] $end
$var wire 3 " opcode [2:0] $end
$var wire 3 # rd [2:0] $end
$var wire 3 $ rs1 [2:0] $end
$var wire 3 % rs2 [2:0] $end
$var wire 4 & unused [3:0] $end
$var reg 8 ' addr [7:0] $end
$var integer 32 ( errors [31:0] $end
$var integer 32 ) i [31:0] $end
$scope module uut $end
$var wire 8 * addr [7:0] $end
$var integer 32 + i [31:0] $end
$var reg 16 , instruction [15:0] $end
$upscope $end
$scope task check_instruction $end
$var reg 16 - expected [15:0] $end
$var reg 8 . test_addr [7:0] $end
$upscope $end
$upscope $end
$enddefinitions $end
#0
$dumpvars
b0 .
b10100110000 -
b10100110000 ,
b100000000 +
b0 *
bx )
b0 (
b0 '
b0 &
b11 %
b10 $
b1 #
b0 "
b10100110000 !
$end
#5000
b1 $
b100 #
b1 "
b11000010110000 ,
b11000010110000 !
b1 '
b1 *
b11000010110000 -
b1 .
#10000
b10 $
b101 #
b10 "
b101010100110000 ,
b101010100110000 !
b10 '
b10 *
b101010100110000 -
b10 .
#15000
b10 %
b1 $
b110 #
b11 "
b111100010100000 ,
b111100010100000 !
b11 '
b11 *
b111100010100000 -
b11 .
#20000
b0 %
b111 #
b100 "
b1001110010000000 ,
b1001110010000000 !
b100 '
b100 *
b1001110010000000 -
b100 .
#25000
b10 $
b1 #
b101 "
b1010010100000000 ,
b1010010100000000 !
b101 '
b101 *
b1010010100000000 -
b101 .
#30000
b100 &
b0 $
b0 #
b111 "
b1110000000000100 ,
b1110000000000100 !
b110 '
b110 *
b1110000000000100 -
b110 .
#35000
b0 &
b0 "
b0 ,
b0 !
b111 '
b111 *
b0 -
b111 .
#40000
b10000000 '
b10000000 *
b10000000 .
#45000
b11111111 '
b11111111 *
b11111111 .
#50000
b11 %
b10 $
b1 #
b10100110000 ,
b10100110000 !
b0 '
b0 *
b10100110000 -
b0 .
#55000
b0 )
#56000
b1 $
b100 #
b1 "
b11000010110000 ,
b11000010110000 !
b1 '
b1 *
b1 )
#57000
b10 $
b101 #
b10 "
b101010100110000 ,
b101010100110000 !
b10 '
b10 *
b10 )
#58000
b10 %
b1 $
b110 #
b11 "
b111100010100000 ,
b111100010100000 !
b11 '
b11 *
b11 )
#59000
b0 %
b111 #
b100 "
b1001110010000000 ,
b1001110010000000 !
b100 '
b100 *
b100 )
#60000
b10 $
b1 #
b101 "
b1010010100000000 ,
b1010010100000000 !
b101 '
b101 *
b101 )
#61000
b100 &
b0 $
b0 #
b111 "
b1110000000000100 ,
b1110000000000100 !
b110 '
b110 *
b110 )
#62000
b0 &
b0 "
b0 ,
b0 !
b111 '
b111 *
b111 )
#63000
b1000 '
b1000 *
b1000 )
#64000
b1001 '
b1001 *
b1001 )
#65000
b1010 )
