register_file.v
module register_file(
    input clk,
    input rst,
    input write_enable,
    input [2:0] read_addr1, // Address of first source register
    input [2:0] read_addr2, // Address of second source register
    input [2:0] write_addr, // Address of destination register
    input [7:0] write_data, // Data to be written to the destination register
    output reg[7:0] read_data1, // Data from first source register
    output reg[7:0] read_data2 // Data from second source register
);
    integer i;

    reg [7:0] registers [0:7];
    always @(*) begin

        read_data1 = (write_enable && (read_addr1 == write_addr)) ? write_data : registers[read_addr1]; // rectifying the read-before-write hazard
        read_data2 = (write_enable && (read_addr2 == write_addr)) ? write_data : registers[read_addr2];
    end

    always @(posedge clk or posedge rst) begin
        
        if(rst) begin
            for(i=0; i<8; i=i+1)begin
                registers[i] <= 8'b0;
            end

        end else if(write_enable) begin
            registers[write_addr] <= write_data;
        end
    end
endmodule

register_file_tb.v
module register_file_tb;

    // Inputs
    reg clk;
    reg rst;
    reg write_enable;
    reg [2:0] read_addr1;
    reg [2:0] read_addr2;
    reg [2:0] write_addr;
    reg [7:0] write_data;

    // Outputs
    wire [7:0] read_data1;
    wire [7:0] read_data2;

    // Instantiate register file
    register_file uut(
        .clk(clk),
        .rst(rst),
        .write_enable(write_enable),
        .read_addr1(read_addr1),
        .read_addr2(read_addr2),
        .write_addr(write_addr),
        .write_data(write_data),
        .read_data1(read_data1),
        .read_data2(read_data2)
    );

    // Clock generation — 10ns period
    initial clk = 0;
    always #5 clk = ~clk;

    // Monitor
    initial begin
        $monitor("Time=%0t | rst=%b | we=%b | waddr=%0d | wdata=%0d | raddr1=%0d | rdata1=%0d | raddr2=%0d | rdata2=%0d",
                  $time, rst, write_enable, write_addr, write_data,
                  read_addr1, read_data1, read_addr2, read_data2);
    end

    initial begin
        $dumpfile("register_file_tb.vcd");
        $dumpvars(0, register_file_tb);

        // -------------------------
        // Test 1 — Reset
        // -------------------------
        rst = 1; write_enable = 0;
        read_addr1 = 0; read_addr2 = 0;
        write_addr = 0; write_data = 0;
        #10;
        rst = 0;
        #10;
        // Verify all registers are 0 after reset
        read_addr1 = 3'd0; read_addr2 = 3'd7; #10;

        // -------------------------
        // Test 2 — Write then Read
        // -------------------------
        // Write 42 to R3
        write_enable = 1;
        write_addr = 3'd3;
        write_data = 8'd42;
        #10;
        write_enable = 0;
        // Read R3 back
        read_addr1 = 3'd3;
        #10;
        // Expected: read_data1 = 42

        // -------------------------
        // Test 3 — Write to multiple registers
        // -------------------------
        // Write 99 to R1
        write_enable = 1;
        write_addr = 3'd1;
        write_data = 8'd99;
        #10;
        // Write 55 to R5
        write_addr = 3'd5;
        write_data = 8'd55;
        #10;
        write_enable = 0;
        // Read R1 and R5 simultaneously
        read_addr1 = 3'd1;
        read_addr2 = 3'd5;
        #10;
        // Expected: read_data1 = 99, read_data2 = 55

        // -------------------------
        // Test 4 — Write enable = 0
        // -------------------------
        // Try writing to R3 with write_enable off
        write_enable = 0;
        write_addr = 3'd3;
        write_data = 8'd255;
        #10;
        // Read R3 — should still be 42
        read_addr1 = 3'd3;
        #10;
        // Expected: read_data1 = 42, not 255

        // -------------------------
        // Test 5 — Data Forwarding
        // -------------------------
        // Write 77 to R2 and read R2 in the same cycle
        write_enable = 1;
        write_addr = 3'd2;
        write_data = 8'd77;
        read_addr1 = 3'd2; // Reading same address being written
        #10;
        // Expected: read_data1 = 77 (forwarded, not old value)
        write_enable = 0;

        // -------------------------
        // Test 6 — Reset clears everything
        // -------------------------
        rst = 1; #10;
        rst = 0;
        read_addr1 = 3'd3; // Was 42
        read_addr2 = 3'd1; // Was 99
        #10;
        // Expected: both read_data = 0

        $finish;
    end

endmodule

vcd/register_file_tb.vcd
$date
	Sun Jun 21 22:34:43 2026
$end
$version
	Icarus Verilog
$end
$timescale
	1s
$end
$scope module register_file_tb $end
$var wire 8 ! read_data1 [7:0] $end
$var wire 8 " read_data2 [7:0] $end
$var reg 1 # clk $end
$var reg 3 $ read_addr1 [2:0] $end
$var reg 3 % read_addr2 [2:0] $end
$var reg 1 & rst $end
$var reg 3 ' write_addr [2:0] $end
$var reg 8 ( write_data [7:0] $end
$var reg 1 ) write_enable $end
$scope module uut $end
$var wire 1 * clk $end
$var wire 3 + read_addr1 [2:0] $end
$var wire 3 , read_addr2 [2:0] $end
$var wire 1 - rst $end
$var wire 3 . write_addr [2:0] $end
$var wire 8 / write_data [7:0] $end
$var wire 1 0 write_enable $end
$var integer 32 1 i [31:0] $end
$var reg 8 2 read_data1 [7:0] $end
$var reg 8 3 read_data2 [7:0] $end
$upscope $end
$upscope $end
$enddefinitions $end
#0
$dumpvars
b0 3
b0 2
b1000 1
00
b0 /
b0 .
1-
b0 ,
b0 +
0*
0)
b0 (
b0 '
1&
b0 %
b0 $
0#
b0 "
b0 !
$end
#5
b1000 1
1#
1*
#10
0#
0*
0&
0-
#15
1#
1*
#20
0#
0*
b111 %
b111 ,
#25
1#
1*
#30
0#
0*
b101010 (
b101010 /
b11 '
b11 .
1)
10
#35
1#
1*
#40
b101010 2
b101010 !
0#
0*
b11 $
b11 +
0)
00
#45
1#
1*
#50
0#
0*
b1100011 (
b1100011 /
b1 '
b1 .
1)
10
#55
1#
1*
#60
0#
0*
b110111 (
b110111 /
b101 '
b101 .
#65
1#
1*
#70
b110111 3
b110111 "
b1100011 2
b1100011 !
0#
0*
b101 %
b101 ,
b1 $
b1 +
0)
00
#75
1#
1*
#80
0#
0*
b11111111 (
b11111111 /
b11 '
b11 .
#85
1#
1*
#90
b101010 2
b101010 !
0#
0*
b11 $
b11 +
#95
1#
1*
#100
b1001101 2
b1001101 !
0#
0*
b10 $
b10 +
b1001101 (
b1001101 /
b10 '
b10 .
1)
10
#105
1#
1*
#110
b0 3
b0 "
b0 2
b0 !
b1000 1
0#
0*
1&
1-
0)
00
#115
b1000 1
1#
1*
#120
0#
0*
b1 %
b1 ,
b11 $
b11 +
0&
0-
